package_name/__init__.py
package_name/module1_name/__init__.py
package_name/module1_name/main.py
sistme_bancario-0.0.1.dist-info/METADATA
sistme_bancario-0.0.1.dist-info/WHEEL
sistme_bancario-0.0.1.dist-info/top_level.txt
sistme_bancario-0.0.1.dist-info/RECORD
