Metadata-Version: 2.4
Name: sistme_bancario
Version: 0.0.1
Summary: Sistema bancário com python
Home-page: https://github.com/Raphael2203/diostudy/blob/main/sistema_bancario2.py
Author: Raphael
Author-email: pererap015@gmail.com
Requires-Python: >=3.8
Dynamic: author
Dynamic: author-email
Dynamic: description
Dynamic: description-content-type
Dynamic: home-page
Dynamic: requires-python
Dynamic: summary
